nti.nose_traceback_info-1.0.2-py2.7-nspkg.pth
nti/nose_traceback_info/__init__.py
nti/nose_traceback_info/tests/__init__.py
nti/nose_traceback_info/tests/test_nose_traceback_info.py
nti.nose_traceback_info-1.0.2.dist-info/DESCRIPTION.rst
nti.nose_traceback_info-1.0.2.dist-info/entry_points.txt
nti.nose_traceback_info-1.0.2.dist-info/METADATA
nti.nose_traceback_info-1.0.2.dist-info/metadata.json
nti.nose_traceback_info-1.0.2.dist-info/namespace_packages.txt
nti.nose_traceback_info-1.0.2.dist-info/RECORD
nti.nose_traceback_info-1.0.2.dist-info/top_level.txt
nti.nose_traceback_info-1.0.2.dist-info/WHEEL
