Metadata-Version: 2.0
Name: nti.nose-traceback-info
Version: 1.0.2
Summary: Include __traceback_info__ in tracebacks printed by nose
Home-page: https://github.com/NextThought/nti.nose_traceback_info
Author: Jason Madden
Author-email: open-source@nextthought.com
License: Apache
Keywords: nose exceptions zope
Platform: UNKNOWN
Classifier: Development Status :: 5 - Production/Stable
Classifier: Intended Audience :: Developers
Classifier: License :: OSI Approved :: Apache Software License
Classifier: Natural Language :: English
Classifier: Operating System :: OS Independent
Classifier: Programming Language :: Python :: 2
Classifier: Programming Language :: Python :: 2.7
Classifier: Programming Language :: Python :: 3
Classifier: Programming Language :: Python :: 3.2
Classifier: Programming Language :: Python :: 3.3
Classifier: Programming Language :: Python :: 3.4
Classifier: Topic :: Software Development :: Testing
Classifier: Programming Language :: Python :: Implementation :: CPython
Classifier: Programming Language :: Python :: Implementation :: PyPy
Classifier: Framework :: Zope3
Requires-Dist: setuptools
Requires-Dist: nose (>=1.3.0)
Requires-Dist: zope.exceptions (>=4.0.6)
